{"ongoing_trials": {}, "hyperparameters": {"space": [{"class_name": "Choice", "config": {"name": "lstm_units", "default": 32, "conditions": [], "values": [32, 64, 100, 128], "ordered": true}}, {"class_name": "Choice", "config": {"name": "dropout_rate", "default": 0.1, "conditions": [], "values": [0.1, 0.2, 0.3], "ordered": true}}, {"class_name": "Choice", "config": {"name": "dense_units", "default": 16, "conditions": [], "values": [16, 25, 50], "ordered": true}}], "values": {"lstm_units": 32, "dropout_rate": 0.1, "dense_units": 16}}, "start_order": ["0", "1", "2"], "end_order": ["0", "1", "2"], "run_times": {"0": 1, "1": 1, "2": 1}, "retry_queue": [], "seed": 6381, "seed_state": 6390, "tried_so_far": ["f33ee03ef568005372ce0893041a9d56", "a4aa0113eb28acb84a6f0037ebdc0773", "e4a26dd1517cd3672432fcfdf20f6e66"], "id_to_hash": {"0": "a4aa0113eb28acb84a6f0037ebdc0773", "1": "f33ee03ef568005372ce0893041a9d56", "2": "e4a26dd1517cd3672432fcfdf20f6e66"}, "display": {"search_start": "2025-04-03T16:30:36.995220", "trial_start": {"0": "2025-04-03T16:30:36.995220", "1": "2025-04-03T16:30:54.365956", "2": "2025-04-03T16:32:19.862909"}, "trial_number": {"0": 1, "1": 2, "2": 3}}}