{"ongoing_trials": {}, "hyperparameters": {"space": [{"class_name": "Choice", "config": {"name": "lstm_units", "default": 32, "conditions": [], "values": [32, 50, 64, 100], "ordered": true}}, {"class_name": "Choice", "config": {"name": "dropout_rate", "default": 0.1, "conditions": [], "values": [0.1, 0.2, 0.3], "ordered": true}}, {"class_name": "Choice", "config": {"name": "dense_units", "default": 16, "conditions": [], "values": [16, 25, 50], "ordered": true}}], "values": {"lstm_units": 32, "dropout_rate": 0.1, "dense_units": 16}}, "start_order": ["0", "1", "2", "3", "4"], "end_order": ["0", "1", "2", "3", "4"], "run_times": {"0": 1, "1": 1, "2": 1, "3": 1, "4": 1}, "retry_queue": [], "seed": 2925, "seed_state": 2940, "tried_so_far": ["4360aaf3ece766972685c2286783a0c7", "af8a7176ceeac884dd990d6280eda2b6", "0dd56606414b67710de7d2c16776c94f", "5cbe8641a00830c39a3162626c7f9659", "e4a26dd1517cd3672432fcfdf20f6e66"], "id_to_hash": {"0": "e4a26dd1517cd3672432fcfdf20f6e66", "1": "5cbe8641a00830c39a3162626c7f9659", "2": "af8a7176ceeac884dd990d6280eda2b6", "3": "4360aaf3ece766972685c2286783a0c7", "4": "0dd56606414b67710de7d2c16776c94f"}, "display": {"search_start": "2025-04-08T20:16:37.514854", "trial_start": {"0": "2025-04-08T20:16:37.514854", "1": "2025-04-08T20:17:05.609985", "2": "2025-04-08T20:18:07.711354", "3": "2025-04-08T20:18:46.042676", "4": "2025-04-08T20:19:32.644767"}, "trial_number": {"0": 1, "1": 2, "2": 3, "3": 4, "4": 5}}}